{
  "title": "Consumer Technology Facts And Digital Behavior angle 18 in under 60 seconds",
  "description": "Topic: Consumer Technology Facts And Digital Behavior angle 18\nNiche: consumer technology facts and digital behavior\nHook: Most people get consumer technology facts and digital behavior angle 18 wrong for one.\nCTA: Follow for more smart tech facts.",
  "hashtags": [
    "#TechFacts",
    "#TechShorts",
    "#AI",
    "#Gadgets",
    "#SmartExplainers",
    "#Consumer",
    "#Technology",
    "#Facts"
  ],
  "generated_at": "2026-04-01T13:58:52.225068Z",
  "prompt_template": "Generate metadata for short-form video publishing.\nRequired fields:\n- title\n- description\n- hashtags\n- keep title sharp and mobile-friendly\n"
}
